{"20171225173956994_320.jpg22020":{"filename":"20171225173956994_320.jpg","size":"22020","regions":[{"shape_attributes":{"name":"rect","x":110,"y":44,"width":127,"height":169},"region_attributes":{"type":"tops","name":"jacket"}},{"shape_attributes":{"name":"rect","x":112,"y":197,"width":93,"height":178},"region_attributes":{"type":"bottoms"}}],"file_attributes":{}},"20171225173645827_320.jpg19345":{"filename":"20171225173645827_320.jpg","size":"19345","regions":[{"shape_attributes":{"name":"rect","x":101,"y":61,"width":123,"height":229},"region_attributes":{"type":"tops"}},{"shape_attributes":{"name":"rect","x":118,"y":289,"width":85,"height":91},"region_attributes":{"type":"bottoms"}}],"file_attributes":{}},"20171225173534081_320.jpg18452":{"filename":"20171225173534081_320.jpg","size":"18452","regions":[{"shape_attributes":{"name":"rect","x":101,"y":64,"width":122,"height":222},"region_attributes":{"type":"tops"}},{"shape_attributes":{"name":"rect","x":96,"y":244,"width":109,"height":134},"region_attributes":{"type":"bottoms"}}],"file_attributes":{}},"20171225173430003_320.jpg17799":{"filename":"20171225173430003_320.jpg","size":"17799","regions":[{"shape_attributes":{"name":"rect","x":100,"y":69,"width":129,"height":214},"region_attributes":{"tops":"","type":"tops"}},{"shape_attributes":{"name":"rect","x":128,"y":219,"width":86,"height":157},"region_attributes":{"type":"bottoms"}}],"file_attributes":{}},"20171225164915194_320.jpg19185":{"filename":"20171225164915194_320.jpg","size":"19185","regions":[{"shape_attributes":{"name":"rect","x":120,"y":53,"width":114,"height":224},"region_attributes":{"type":"tops"}},{"shape_attributes":{"name":"rect","x":134,"y":197,"width":77,"height":185},"region_attributes":{"type":"bottoms"}}],"file_attributes":{}},"20171225164759966_320.jpg20397":{"filename":"20171225164759966_320.jpg","size":"20397","regions":[{"shape_attributes":{"name":"rect","x":107,"y":56,"width":126,"height":166},"region_attributes":{"type":"tops"}},{"shape_attributes":{"name":"rect","x":112,"y":202,"width":97,"height":183},"region_attributes":{"type":"bottoms"}}],"file_attributes":{}},"20171225164620663_320.jpg20746":{"filename":"20171225164620663_320.jpg","size":"20746","regions":[{"shape_attributes":{"name":"rect","x":91,"y":58,"width":130,"height":163},"region_attributes":{"type":"tops"}},{"shape_attributes":{"name":"rect","x":106,"y":192,"width":100,"height":195},"region_attributes":{"type":"bottoms"}}],"file_attributes":{}},"20171225162848182_320.jpg21330":{"filename":"20171225162848182_320.jpg","size":"21330","regions":[{"shape_attributes":{"name":"rect","x":103,"y":60,"width":129,"height":166},"region_attributes":{"type":"tops"}},{"shape_attributes":{"name":"rect","x":121,"y":208,"width":88,"height":164},"region_attributes":{"type":"bottoms"}}],"file_attributes":{}},"20171225162710428_320.jpg19640":{"filename":"20171225162710428_320.jpg","size":"19640","regions":[{"shape_attributes":{"name":"rect","x":106,"y":61,"width":131,"height":157},"region_attributes":{"type":"tops"}},{"shape_attributes":{"name":"rect","x":122,"y":209,"width":78,"height":172},"region_attributes":{"type":"bottoms"}}],"file_attributes":{}},"20171225162510669_320.jpg23337":{"filename":"20171225162510669_320.jpg","size":"23337","regions":[{"shape_attributes":{"name":"rect","x":76,"y":21,"width":155,"height":202},"region_attributes":{"type":"tops"}},{"shape_attributes":{"name":"rect","x":116,"y":194,"width":98,"height":193},"region_attributes":{"type":"bottoms"}}],"file_attributes":{}},"20171225162354653_320.jpg20560":{"filename":"20171225162354653_320.jpg","size":"20560","regions":[{"shape_attributes":{"name":"rect","x":95,"y":62,"width":126,"height":159},"region_attributes":{"tops":"","bottoms":"","type":"tops"}},{"shape_attributes":{"name":"rect","x":98,"y":193,"width":113,"height":191},"region_attributes":{"tops":"","bottoms":"","type":"bottoms"}}],"file_attributes":{}},"20171225145436707_320.jpg19599":{"filename":"20171225145436707_320.jpg","size":"19599","regions":[{"shape_attributes":{"name":"rect","x":90,"y":55,"width":134,"height":162},"region_attributes":{"type":"tops"}},{"shape_attributes":{"name":"rect","x":111,"y":204,"width":82,"height":174},"region_attributes":{"type":"bottoms"}}],"file_attributes":{}},"20171225145157145_320.jpg20146":{"filename":"20171225145157145_320.jpg","size":"20146","regions":[{"shape_attributes":{"name":"rect","x":96,"y":63,"width":135,"height":209},"region_attributes":{"type":"tops"}},{"shape_attributes":{"name":"rect","x":115,"y":203,"width":85,"height":171},"region_attributes":{"type":"bottoms"}}],"file_attributes":{}},"20171225144932759_320.jpg18567":{"filename":"20171225144932759_320.jpg","size":"18567","regions":[{"shape_attributes":{"name":"rect","x":100,"y":67,"width":141,"height":211},"region_attributes":{"type":"tops"}},{"shape_attributes":{"name":"rect","x":105,"y":190,"width":87,"height":179},"region_attributes":{"type":"bottoms"}}],"file_attributes":{}},"20171225121236091_320.jpg17791":{"filename":"20171225121236091_320.jpg","size":"17791","regions":[{"shape_attributes":{"name":"rect","x":104,"y":58,"width":107,"height":227},"region_attributes":{"type":"tops"}},{"shape_attributes":{"name":"rect","x":117,"y":199,"width":83,"height":179},"region_attributes":{"type":"bottoms"}}],"file_attributes":{}},"20171225114735520_320.jpg22758":{"filename":"20171225114735520_320.jpg","size":"22758","regions":[{"shape_attributes":{"name":"rect","x":93,"y":56,"width":137,"height":168},"region_attributes":{"type":"tops"}},{"shape_attributes":{"name":"rect","x":97,"y":176,"width":101,"height":206},"region_attributes":{"type":"bottoms"}}],"file_attributes":{}},"20171222162756284_320.jpg18910":{"filename":"20171222162756284_320.jpg","size":"18910","regions":[{"shape_attributes":{"name":"rect","x":108,"y":55,"width":125,"height":156},"region_attributes":{"type":"tops"}},{"shape_attributes":{"name":"rect","x":113,"y":188,"width":93,"height":196},"region_attributes":{"type":"bottoms"}}],"file_attributes":{}},"20171222162437897_320.jpg20079":{"filename":"20171222162437897_320.jpg","size":"20079","regions":[{"shape_attributes":{"name":"rect","x":90,"y":60,"width":128,"height":165},"region_attributes":{"type":"tops"}},{"shape_attributes":{"name":"rect","x":107,"y":189,"width":80,"height":193},"region_attributes":{"type":"bottoms"}}],"file_attributes":{}},"20171222161845443_320.jpg18437":{"filename":"20171222161845443_320.jpg","size":"18437","regions":[{"shape_attributes":{"name":"rect","x":105,"y":56,"width":127,"height":208},"region_attributes":{"type":"tops"}},{"shape_attributes":{"name":"rect","x":116,"y":193,"width":88,"height":185},"region_attributes":{"type":"bottoms"}}],"file_attributes":{}},"20171222161713069_320.jpg18652":{"filename":"20171222161713069_320.jpg","size":"18652","regions":[{"shape_attributes":{"name":"rect","x":105,"y":52,"width":118,"height":169},"region_attributes":{"type":"tops"}},{"shape_attributes":{"name":"rect","x":104,"y":192,"width":95,"height":193},"region_attributes":{"type":"bottoms"}}],"file_attributes":{}},"20171222124202331_320.jpg22668":{"filename":"20171222124202331_320.jpg","size":"22668","regions":[{"shape_attributes":{"name":"rect","x":105,"y":68,"width":129,"height":206},"region_attributes":{"type":"tops"}},{"shape_attributes":{"name":"rect","x":110,"y":166,"width":99,"height":207},"region_attributes":{"type":"bottoms"}}],"file_attributes":{}},"20171222122200194_320.jpg21764":{"filename":"20171222122200194_320.jpg","size":"21764","regions":[{"shape_attributes":{"name":"rect","x":103,"y":57,"width":136,"height":160},"region_attributes":{"type":"tops"}},{"shape_attributes":{"name":"rect","x":101,"y":199,"width":103,"height":188},"region_attributes":{"type":"bottoms"}}],"file_attributes":{}},"20171222122020879_320.jpg20556":{"filename":"20171222122020879_320.jpg","size":"20556","regions":[{"shape_attributes":{"name":"rect","x":96,"y":62,"width":133,"height":168},"region_attributes":{"type":"tops"}},{"shape_attributes":{"name":"rect","x":118,"y":200,"width":77,"height":182},"region_attributes":{"type":"bottoms"}}],"file_attributes":{}},"20171211171436296_320.jpg19606":{"filename":"20171211171436296_320.jpg","size":"19606","regions":[{"shape_attributes":{"name":"rect","x":100,"y":67,"width":136,"height":159},"region_attributes":{"type":"tops"}},{"shape_attributes":{"name":"rect","x":112,"y":207,"width":94,"height":175},"region_attributes":{"type":"bottoms"}}],"file_attributes":{}},"20171211171248123_320.jpg20473":{"filename":"20171211171248123_320.jpg","size":"20473","regions":[{"shape_attributes":{"name":"rect","x":110,"y":52,"width":113,"height":158},"region_attributes":{"type":"tops"}},{"shape_attributes":{"name":"rect","x":110,"y":189,"width":105,"height":194},"region_attributes":{"type":"bottoms"}}],"file_attributes":{}},"20171211170919342_320.jpg19194":{"filename":"20171211170919342_320.jpg","size":"19194","regions":[{"shape_attributes":{"name":"rect","x":110,"y":62,"width":124,"height":233},"region_attributes":{"type":"tops"}},{"shape_attributes":{"name":"rect","x":129,"y":191,"width":79,"height":197},"region_attributes":{"type":"bottoms"}}],"file_attributes":{}},"20171211170730501_320.jpg23034":{"filename":"20171211170730501_320.jpg","size":"23034","regions":[{"shape_attributes":{"name":"rect","x":105,"y":50,"width":124,"height":165},"region_attributes":{"type":"tops"}},{"shape_attributes":{"name":"rect","x":108,"y":183,"width":112,"height":201},"region_attributes":{"type":"bottoms"}}],"file_attributes":{}},"20171211170332923_320.jpg19708":{"filename":"20171211170332923_320.jpg","size":"19708","regions":[{"shape_attributes":{"name":"rect","x":101,"y":59,"width":130,"height":158},"region_attributes":{"type":"tops"}},{"shape_attributes":{"name":"rect","x":107,"y":187,"width":101,"height":188},"region_attributes":{"type":"bottoms"}}],"file_attributes":{}},"20171211162946402_320.jpg17877":{"filename":"20171211162946402_320.jpg","size":"17877","regions":[{"shape_attributes":{"name":"rect","x":108,"y":67,"width":121,"height":235},"region_attributes":{"type":"tops"}},{"shape_attributes":{"name":"rect","x":113,"y":208,"width":93,"height":177},"region_attributes":{"type":"bottoms"}}],"file_attributes":{}},"20171211162805156_320.jpg21243":{"filename":"20171211162805156_320.jpg","size":"21243","regions":[{"shape_attributes":{"name":"rect","x":107,"y":54,"width":131,"height":223},"region_attributes":{"type":"tops"}},{"shape_attributes":{"name":"rect","x":118,"y":180,"width":92,"height":208},"region_attributes":{"type":"bottoms"}}],"file_attributes":{}},"20171211162638370_320.jpg21572":{"filename":"20171211162638370_320.jpg","size":"21572","regions":[],"file_attributes":{}},"20171211162434945_320.jpg20901":{"filename":"20171211162434945_320.jpg","size":"20901","regions":[],"file_attributes":{}},"20171211162310171_320.jpg19872":{"filename":"20171211162310171_320.jpg","size":"19872","regions":[],"file_attributes":{}},"20171211162149445_320.jpg19966":{"filename":"20171211162149445_320.jpg","size":"19966","regions":[],"file_attributes":{}},"20171211161236779_320.jpg18492":{"filename":"20171211161236779_320.jpg","size":"18492","regions":[],"file_attributes":{}},"20171211122523514_320.jpg19119":{"filename":"20171211122523514_320.jpg","size":"19119","regions":[],"file_attributes":{}},"20171211122314213_320.jpg21366":{"filename":"20171211122314213_320.jpg","size":"21366","regions":[],"file_attributes":{}},"20171211121723593_320.jpg18704":{"filename":"20171211121723593_320.jpg","size":"18704","regions":[],"file_attributes":{}},"20171211121538148_320.jpg20258":{"filename":"20171211121538148_320.jpg","size":"20258","regions":[],"file_attributes":{}},"20171211121415030_320.jpg19835":{"filename":"20171211121415030_320.jpg","size":"19835","regions":[],"file_attributes":{}},"20171211121045945_320.jpg20452":{"filename":"20171211121045945_320.jpg","size":"20452","regions":[],"file_attributes":{}},"20171211120823894_320.jpg19240":{"filename":"20171211120823894_320.jpg","size":"19240","regions":[],"file_attributes":{}},"20171211115638964_320.jpg22390":{"filename":"20171211115638964_320.jpg","size":"22390","regions":[],"file_attributes":{}},"20171211115506421_320.jpg20504":{"filename":"20171211115506421_320.jpg","size":"20504","regions":[],"file_attributes":{}},"20171211115027781_320.jpg18688":{"filename":"20171211115027781_320.jpg","size":"18688","regions":[],"file_attributes":{}},"20171211114848771_320.jpg20291":{"filename":"20171211114848771_320.jpg","size":"20291","regions":[],"file_attributes":{}},"20171211114706319_320.jpg19579":{"filename":"20171211114706319_320.jpg","size":"19579","regions":[],"file_attributes":{}},"20171211114441340_320.jpg20596":{"filename":"20171211114441340_320.jpg","size":"20596","regions":[],"file_attributes":{}},"20171208162824546_320.jpg19119":{"filename":"20171208162824546_320.jpg","size":"19119","regions":[],"file_attributes":{}},"20171208162627424_320.jpg22126":{"filename":"20171208162627424_320.jpg","size":"22126","regions":[],"file_attributes":{}},"20171208162509904_320.jpg22074":{"filename":"20171208162509904_320.jpg","size":"22074","regions":[],"file_attributes":{}},"20171208162302063_320.jpg19730":{"filename":"20171208162302063_320.jpg","size":"19730","regions":[],"file_attributes":{}},"20171208161805605_320.jpg20960":{"filename":"20171208161805605_320.jpg","size":"20960","regions":[],"file_attributes":{}},"20171208161701511_320.jpg22424":{"filename":"20171208161701511_320.jpg","size":"22424","regions":[],"file_attributes":{}},"20171208161548414_320.jpg22251":{"filename":"20171208161548414_320.jpg","size":"22251","regions":[],"file_attributes":{}},"20171208160926732_320.jpg19839":{"filename":"20171208160926732_320.jpg","size":"19839","regions":[],"file_attributes":{}},"20171208160803820_320.jpg19702":{"filename":"20171208160803820_320.jpg","size":"19702","regions":[],"file_attributes":{}},"20171208160505317_320.jpg21146":{"filename":"20171208160505317_320.jpg","size":"21146","regions":[],"file_attributes":{}},"20171208125626804_320.jpg21945":{"filename":"20171208125626804_320.jpg","size":"21945","regions":[],"file_attributes":{}},"20171208125435537_320.jpg20994":{"filename":"20171208125435537_320.jpg","size":"20994","regions":[],"file_attributes":{}},"20171208125222817_320.jpg20014":{"filename":"20171208125222817_320.jpg","size":"20014","regions":[],"file_attributes":{}},"20171208125020276_320.jpg19485":{"filename":"20171208125020276_320.jpg","size":"19485","regions":[],"file_attributes":{}},"20171208124722720_320.jpg20604":{"filename":"20171208124722720_320.jpg","size":"20604","regions":[],"file_attributes":{}},"20171208124553373_320.jpg22059":{"filename":"20171208124553373_320.jpg","size":"22059","regions":[],"file_attributes":{}},"20171208124439226_320.jpg21018":{"filename":"20171208124439226_320.jpg","size":"21018","regions":[],"file_attributes":{}},"20171208124259998_320.jpg21010":{"filename":"20171208124259998_320.jpg","size":"21010","regions":[],"file_attributes":{}},"20171208122206472_320.jpg21054":{"filename":"20171208122206472_320.jpg","size":"21054","regions":[],"file_attributes":{}},"20171208122030978_320.jpg22783":{"filename":"20171208122030978_320.jpg","size":"22783","regions":[],"file_attributes":{}},"20171208121902545_320.jpg21398":{"filename":"20171208121902545_320.jpg","size":"21398","regions":[],"file_attributes":{}},"20171208121705084_320.jpg19463":{"filename":"20171208121705084_320.jpg","size":"19463","regions":[],"file_attributes":{}},"20171208121409999_320.jpg22355":{"filename":"20171208121409999_320.jpg","size":"22355","regions":[],"file_attributes":{}},"20171208121235956_320.jpg20677":{"filename":"20171208121235956_320.jpg","size":"20677","regions":[],"file_attributes":{}},"20171208121038966_320.jpg19495":{"filename":"20171208121038966_320.jpg","size":"19495","regions":[],"file_attributes":{}},"20171201171517879_320.jpg23856":{"filename":"20171201171517879_320.jpg","size":"23856","regions":[],"file_attributes":{}},"20171201171204729_320.jpg22277":{"filename":"20171201171204729_320.jpg","size":"22277","regions":[],"file_attributes":{}},"20171201171053496_320.jpg20560":{"filename":"20171201171053496_320.jpg","size":"20560","regions":[],"file_attributes":{}},"20171201165719442_320.jpg20368":{"filename":"20171201165719442_320.jpg","size":"20368","regions":[],"file_attributes":{}},"20171201165503642_320.jpg18869":{"filename":"20171201165503642_320.jpg","size":"18869","regions":[],"file_attributes":{}},"20171201165220862_320.jpg18715":{"filename":"20171201165220862_320.jpg","size":"18715","regions":[],"file_attributes":{}},"20171201162945219_320.jpg21824":{"filename":"20171201162945219_320.jpg","size":"21824","regions":[],"file_attributes":{}},"20171201162713129_320.jpg17894":{"filename":"20171201162713129_320.jpg","size":"17894","regions":[],"file_attributes":{}},"20171201162515945_320.jpg19619":{"filename":"20171201162515945_320.jpg","size":"19619","regions":[],"file_attributes":{}},"20171201143349539_320.jpg19403":{"filename":"20171201143349539_320.jpg","size":"19403","regions":[],"file_attributes":{}},"20171201131906748_320.jpg20286":{"filename":"20171201131906748_320.jpg","size":"20286","regions":[],"file_attributes":{}},"20171201131517977_320.jpg19949":{"filename":"20171201131517977_320.jpg","size":"19949","regions":[],"file_attributes":{}},"20171201130607269_320.jpg20878":{"filename":"20171201130607269_320.jpg","size":"20878","regions":[],"file_attributes":{}},"20171201130055502_320.jpg21009":{"filename":"20171201130055502_320.jpg","size":"21009","regions":[],"file_attributes":{}},"20171201125845622_320.jpg21775":{"filename":"20171201125845622_320.jpg","size":"21775","regions":[],"file_attributes":{}},"20171201120045643_320.jpg17357":{"filename":"20171201120045643_320.jpg","size":"17357","regions":[],"file_attributes":{}},"20171201115517843_320.jpg19275":{"filename":"20171201115517843_320.jpg","size":"19275","regions":[],"file_attributes":{}},"20171201114913123_320.jpg21366":{"filename":"20171201114913123_320.jpg","size":"21366","regions":[],"file_attributes":{}},"20171201114707257_320.jpg19977":{"filename":"20171201114707257_320.jpg","size":"19977","regions":[],"file_attributes":{}},"20171201113816618_320.jpg21275":{"filename":"20171201113816618_320.jpg","size":"21275","regions":[],"file_attributes":{}},"20171201113329598_320.jpg24062":{"filename":"20171201113329598_320.jpg","size":"24062","regions":[],"file_attributes":{}},"20171201113057396_320.jpg20814":{"filename":"20171201113057396_320.jpg","size":"20814","regions":[],"file_attributes":{}},"20171201112823521_320.jpg19846":{"filename":"20171201112823521_320.jpg","size":"19846","regions":[],"file_attributes":{}},"20171130163545395_320.jpg19201":{"filename":"20171130163545395_320.jpg","size":"19201","regions":[],"file_attributes":{}},"20171130163148372_320.jpg21802":{"filename":"20171130163148372_320.jpg","size":"21802","regions":[],"file_attributes":{}},"20171130162916231_320.jpg22081":{"filename":"20171130162916231_320.jpg","size":"22081","regions":[],"file_attributes":{}},"20171130162624674_320.jpg18432":{"filename":"20171130162624674_320.jpg","size":"18432","regions":[],"file_attributes":{}},"20171130161237222_320.jpg22889":{"filename":"20171130161237222_320.jpg","size":"22889","regions":[],"file_attributes":{}},"20171130161004124_320.jpg20632":{"filename":"20171130161004124_320.jpg","size":"20632","regions":[],"file_attributes":{}},"20171130160740371_320.jpg22479":{"filename":"20171130160740371_320.jpg","size":"22479","regions":[],"file_attributes":{}},"20171130144107255_320.jpg18746":{"filename":"20171130144107255_320.jpg","size":"18746","regions":[],"file_attributes":{}},"20171130143639742_320.jpg20601":{"filename":"20171130143639742_320.jpg","size":"20601","regions":[],"file_attributes":{}},"20171130143514494_320.jpg20130":{"filename":"20171130143514494_320.jpg","size":"20130","regions":[],"file_attributes":{}},"20171130143020235_320.jpg19114":{"filename":"20171130143020235_320.jpg","size":"19114","regions":[],"file_attributes":{}},"20171130142844673_320.jpg19674":{"filename":"20171130142844673_320.jpg","size":"19674","regions":[],"file_attributes":{}},"20171130142714051_320.jpg21670":{"filename":"20171130142714051_320.jpg","size":"21670","regions":[],"file_attributes":{}},"20171130131835114_320.jpg22315":{"filename":"20171130131835114_320.jpg","size":"22315","regions":[],"file_attributes":{}},"20171130131708916_320.jpg20280":{"filename":"20171130131708916_320.jpg","size":"20280","regions":[],"file_attributes":{}},"20171130131519115_320.jpg19448":{"filename":"20171130131519115_320.jpg","size":"19448","regions":[],"file_attributes":{}},"20171130115518249_320.jpg19275":{"filename":"20171130115518249_320.jpg","size":"19275","regions":[],"file_attributes":{}},"20171130115344043_320.jpg21133":{"filename":"20171130115344043_320.jpg","size":"21133","regions":[],"file_attributes":{}},"20171130115224212_320.jpg22965":{"filename":"20171130115224212_320.jpg","size":"22965","regions":[],"file_attributes":{}},"20171130115102632_320.jpg20369":{"filename":"20171130115102632_320.jpg","size":"20369","regions":[],"file_attributes":{}},"20171130114933923_320.jpg20835":{"filename":"20171130114933923_320.jpg","size":"20835","regions":[],"file_attributes":{}},"20171130114819407_320.jpg20618":{"filename":"20171130114819407_320.jpg","size":"20618","regions":[],"file_attributes":{}},"20171130114708149_320.jpg21812":{"filename":"20171130114708149_320.jpg","size":"21812","regions":[],"file_attributes":{}},"20171130114536156_320.jpg20969":{"filename":"20171130114536156_320.jpg","size":"20969","regions":[],"file_attributes":{}},"20171129170802554_320.jpg20720":{"filename":"20171129170802554_320.jpg","size":"20720","regions":[],"file_attributes":{}},"20171129170306746_320.jpg21332":{"filename":"20171129170306746_320.jpg","size":"21332","regions":[],"file_attributes":{}},"20171129162456811_320.jpg20526":{"filename":"20171129162456811_320.jpg","size":"20526","regions":[],"file_attributes":{}},"20171129160029199_320.jpg22647":{"filename":"20171129160029199_320.jpg","size":"22647","regions":[],"file_attributes":{}},"20171129155622425_320.jpg23694":{"filename":"20171129155622425_320.jpg","size":"23694","regions":[],"file_attributes":{}},"20171129155421084_320.jpg20363":{"filename":"20171129155421084_320.jpg","size":"20363","regions":[],"file_attributes":{}},"20171129155257825_320.jpg26166":{"filename":"20171129155257825_320.jpg","size":"26166","regions":[],"file_attributes":{}},"20171129155138759_320.jpg25291":{"filename":"20171129155138759_320.jpg","size":"25291","regions":[],"file_attributes":{}},"yamatoshi.jpg35026":{"filename":"yamatoshi.jpg","size":35026,"regions":[{"shape_attributes":{"name":"rect","x":29,"y":89,"width":144,"height":156},"region_attributes":{"type":"tops"}},{"shape_attributes":{"name":"rect","x":33,"y":206,"width":114,"height":149},"region_attributes":{"type":"bottoms"}}],"file_attributes":{}}}